svg_to_gcode/__init__.py
svg_to_gcode/formulas.py
svg_to_gcode/compiler/__init__.py
svg_to_gcode/compiler/_compiler.py
svg_to_gcode/compiler/interfaces/__init__.py
svg_to_gcode/compiler/interfaces/_abstract_interface.py
svg_to_gcode/compiler/interfaces/_fan_controlled_gcode.py
svg_to_gcode/compiler/interfaces/_gcode.py
svg_to_gcode/geometry/__init__.py
svg_to_gcode/geometry/_abstract_chain.py
svg_to_gcode/geometry/_abstract_curve.py
svg_to_gcode/geometry/_circular_arc.py
svg_to_gcode/geometry/_cubic_bazier.py
svg_to_gcode/geometry/_elliptical_arc.py
svg_to_gcode/geometry/_line.py
svg_to_gcode/geometry/_line_segment_chain.py
svg_to_gcode/geometry/_matrix.py
svg_to_gcode/geometry/_quadratic_bazier.py
svg_to_gcode/geometry/_smooth_arc_chain.py
svg_to_gcode/geometry/_vector.py
svg_to_gcode/svg_parser/__init__.py
svg_to_gcode/svg_parser/_helper_functions.py
svg_to_gcode/svg_parser/_parser_methods.py
svg_to_gcode/svg_parser/_path.py
svg_to_gcode/svg_parser/_transformation.py
svg_to_gcode/svg_parser/debug_methods.py
svg_to_gcode-1.5.4.dist-info/LICENSE
svg_to_gcode-1.5.4.dist-info/METADATA
svg_to_gcode-1.5.4.dist-info/WHEEL
svg_to_gcode-1.5.4.dist-info/top_level.txt
svg_to_gcode-1.5.4.dist-info/RECORD
