Metadata-Version: 2.1
Name: svg_to_gcode
Version: 1.5.4
Summary: The definitive NPM module to construct gcode from svg files.
Home-page: https://github.com/PadLex/SvgToGcode
Author: Padlex
Author-email: 
License: UNKNOWN
Platform: UNKNOWN
Classifier: Programming Language :: Python :: 3
Classifier: License :: OSI Approved :: GNU Lesser General Public License v3 (LGPLv3)
Classifier: Operating System :: OS Independent
Requires-Python: >=3.6
